diveplane/openapi/LICENSE-3RD-PARTY.txt
diveplane/openapi/__init__.py
diveplane/openapi/api_client.py
diveplane/openapi/configuration.py
diveplane/openapi/exceptions.py
diveplane/openapi/requirements-3.10.txt
diveplane/openapi/requirements-3.11.txt
diveplane/openapi/requirements-3.8.txt
diveplane/openapi/requirements-3.9.txt
diveplane/openapi/requirements-dev-3.10.txt
diveplane/openapi/requirements-dev-3.11.txt
diveplane/openapi/requirements-dev-3.8.txt
diveplane/openapi/requirements-dev-3.9.txt
diveplane/openapi/requirements-dev.in
diveplane/openapi/requirements.in
diveplane/openapi/rest.py
diveplane/openapi/api/__init__.py
diveplane/openapi/api/account_api.py
diveplane/openapi/api/information_api.py
diveplane/openapi/api/project_management_api.py
diveplane/openapi/api/session_management_api.py
diveplane/openapi/api/task_operations_api.py
diveplane/openapi/api/trainee_case_operations_api.py
diveplane/openapi/api/trainee_defaults_management_api.py
diveplane/openapi/api/trainee_feature_operations_api.py
diveplane/openapi/api/trainee_management_api.py
diveplane/openapi/api/trainee_metrics_api.py
diveplane/openapi/api/trainee_operations_api.py
diveplane/openapi/api/trainee_session_management_api.py
diveplane/openapi/api/trainee_status_api.py
diveplane/openapi/models/__init__.py
diveplane/openapi/models/account.py
diveplane/openapi/models/account_identity.py
diveplane/openapi/models/analyze_request.py
diveplane/openapi/models/append_to_series_store_request.py
diveplane/openapi/models/async_action.py
diveplane/openapi/models/async_action_accepted.py
diveplane/openapi/models/async_action_accepted_tracking.py
diveplane/openapi/models/async_action_cancel.py
diveplane/openapi/models/async_action_cancelled_output.py
diveplane/openapi/models/async_action_complete_output.py
diveplane/openapi/models/async_action_failed_output.py
diveplane/openapi/models/async_action_output.py
diveplane/openapi/models/async_action_status.py
diveplane/openapi/models/base_async_action_output.py
diveplane_openapi_client-24.0.9.dist-info/LICENSE.txt
diveplane_openapi_client-24.0.9.dist-info/METADATA
diveplane_openapi_client-24.0.9.dist-info/WHEEL
diveplane_openapi_client-24.0.9.dist-info/top_level.txt
diveplane_openapi_client-24.0.9.dist-info/RECORD
