Metadata-Version: 2.1
Name: diveplane-openapi-client
Version: 24.0.9
Summary: Diveplane API
Home-page: 
Author: Diveplane Corporation
Author-email: diveplane@diveplane.com
Keywords: OpenAPI,OpenAPI-Generator,Diveplane API
License-File: LICENSE.txt
Requires-Dist: six (>=1.10)
Requires-Dist: python-dateutil (>=2.5.3)
Requires-Dist: setuptools (>=21.0.0)
Requires-Dist: urllib3 (<2.0.0,>=1.25.3)
Requires-Dist: future ; python_version <= "2.7"
